homecom_alt/__init__.py
homecom_alt/const.py
homecom_alt/exceptions.py
homecom_alt/model.py
homecom_alt/py.typed
homecom_alt-1.4.16.dist-info/licenses/LICENSE
homecom_alt-1.4.16.dist-info/METADATA
homecom_alt-1.4.16.dist-info/WHEEL
homecom_alt-1.4.16.dist-info/top_level.txt
homecom_alt-1.4.16.dist-info/RECORD
