Metadata-Version: 2.4
Name: homecom_alt
Version: 1.4.16
Summary: Python wrapper for controlling devices managed by HomeCom Easy APP.
Home-page: https://github.com/serbanb11/homecom-alt
Author: serbanb11
License: MIT
Classifier: Development Status :: 3 - Alpha
Classifier: License :: OSI Approved :: MIT License
Classifier: Operating System :: OS Independent
Classifier: Programming Language :: Python
Classifier: Programming Language :: Python :: 3
Classifier: Programming Language :: Python :: 3.12
Classifier: Programming Language :: Python :: 3.13
Classifier: Programming Language :: Python :: 3 :: Only
Classifier: Typing :: Typed
Requires-Python: >=3.12
License-File: LICENSE
Requires-Dist: aiohttp>=3.9.4
Requires-Dist: tenacity
Requires-Dist: PyJWT>=2.1.0
Dynamic: author
Dynamic: classifier
Dynamic: description
Dynamic: description-content-type
Dynamic: home-page
Dynamic: license
Dynamic: license-file
Dynamic: requires-dist
Dynamic: requires-python
Dynamic: summary
